traffic/__init__.py
traffic/__main__.py
traffic/py.typed
traffic/traffic.conf
traffic/algorithms/__init__.py
traffic/algorithms/clustering.py
traffic/algorithms/cpa.py
traffic/algorithms/douglas_peucker.py
traffic/algorithms/generation.py
traffic/algorithms/filters/__init__.py
traffic/algorithms/filters/aggressive.py
traffic/algorithms/filters/consistency.py
traffic/algorithms/filters/ekf.py
traffic/algorithms/filters/kalman.py
traffic/algorithms/ground/__init__.py
traffic/algorithms/ground/graphs.py
traffic/algorithms/ground/kalman_taxiway.py
traffic/algorithms/ground/movement.py
traffic/algorithms/ground/parking_position.py
traffic/algorithms/ground/pushback.py
traffic/algorithms/ground/runway.py
traffic/algorithms/metadata/__init__.py
traffic/algorithms/metadata/airports.py
traffic/algorithms/metadata/flightplan.py
traffic/algorithms/navigation/__init__.py
traffic/algorithms/navigation/alignment.py
traffic/algorithms/navigation/go_around.py
traffic/algorithms/navigation/landing.py
traffic/algorithms/navigation/phases.py
traffic/algorithms/navigation/point_merge.py
traffic/algorithms/navigation/takeoff.py
traffic/algorithms/navigation/thermals.py
traffic/algorithms/navigation/holding_pattern/__init__.py
traffic/algorithms/navigation/holding_pattern/classifier.onnx
traffic/algorithms/navigation/holding_pattern/scaler.onnx
traffic/algorithms/performance/__init__.py
traffic/algorithms/performance/openap.py
traffic/algorithms/prediction/__init__.py
traffic/algorithms/prediction/flightplan.py
traffic/algorithms/prediction/straightline.py
traffic/console/__init__.py
traffic/console/cache.py
traffic/console/config.py
traffic/console/data.py
traffic/console/opensky.py
traffic/console/show.py
traffic/core/__init__.py
traffic/core/airspace.py
traffic/core/cache.py
traffic/core/distance.py
traffic/core/flight.py
traffic/core/flightplan.py
traffic/core/intervals.py
traffic/core/iterator.py
traffic/core/lazy.py
traffic/core/mixins.py
traffic/core/readme.md
traffic-2.12.dist-info/METADATA
traffic-2.12.dist-info/WHEEL
traffic-2.12.dist-info/entry_points.txt
traffic-2.12.dist-info/RECORD
