Metadata-Version: 2.4
Name: traffic
Version: 2.12
Summary: A toolbox for manipulating and analysing air traffic data
Project-URL: Documentation, https://traffic-viz.github.io/
Project-URL: Code, https://github.com/xoolive/traffic/
Project-URL: Issues, https://github.com/xoolive/traffic/issues/
Project-URL: Releases, https://github.com/xoolive/traffic/releases/
Author-email: Xavier Olive <git@xoolive.org>
License-Expression: MIT
Classifier: Development Status :: 5 - Production/Stable
Classifier: Intended Audience :: Information Technology
Classifier: Intended Audience :: Science/Research
Classifier: License :: OSI Approved :: MIT License
Classifier: Operating System :: MacOS
Classifier: Operating System :: Microsoft :: Windows
Classifier: Operating System :: POSIX :: Linux
Classifier: Programming Language :: Python :: 3
Classifier: Programming Language :: Python :: 3.10
Classifier: Programming Language :: Python :: 3.11
Classifier: Programming Language :: Python :: 3.12
Classifier: Programming Language :: Python :: 3.13
Classifier: Topic :: Scientific/Engineering :: Artificial Intelligence
Classifier: Topic :: Scientific/Engineering :: GIS
Classifier: Topic :: Scientific/Engineering :: Information Analysis
Classifier: Topic :: Scientific/Engineering :: Visualization
Classifier: Topic :: Software Development :: Libraries
Classifier: Typing :: Typed
Requires-Python: >=3.10
Requires-Dist: cartes>=0.8.4
Requires-Dist: httpx>=0.27.2
Requires-Dist: impunity>=1.0.4
Requires-Dist: metar>=1.11.0
Requires-Dist: onnxruntime>=1.19.2
Requires-Dist: openap>=2.0
Requires-Dist: pitot>=0.3.1
Requires-Dist: py7zr>=0.22.0
Requires-Dist: pyarrow>=18.0.0
Requires-Dist: pyopensky>=2.11
Requires-Dist: python-dotenv>=1.0.1
Requires-Dist: rich>=13.9.4
Requires-Dist: rs1090>=0.4.4
Requires-Dist: typing-extensions>=4.12.2
Provides-Extra: altair
Requires-Dist: altair>=5.4.1; extra == 'altair'
Provides-Extra: leaflet
Requires-Dist: ipyleaflet>=0.19.2; extra == 'leaflet'
Requires-Dist: ipywidgets>=8.1.5; extra == 'leaflet'
Provides-Extra: learning
Requires-Dist: scikit-learn>=1.5.2; extra == 'learning'
Provides-Extra: lonboard
Requires-Dist: lonboard>=0.10.3; (python_version < '3.13') and extra == 'lonboard'
Provides-Extra: plotly
Requires-Dist: plotly>=5.24.1; extra == 'plotly'
Provides-Extra: spark
Requires-Dist: pyspark>=3.5.3; extra == 'spark'
Provides-Extra: xarray
Requires-Dist: xarray>=2024.10.0; extra == 'xarray'
